sparcs/__init__.py
sparcs/__main__.py
sparcs/_version.py
sparcs/location.py
sparcs/system.py
sparcs/application/__init__.py
sparcs/application/view/__init__.py
sparcs/application/view/weather.py
sparcs/application/view/agriculture/__init__.py
sparcs/application/view/agriculture/area.py
sparcs/application/view/agriculture/field.py
sparcs/application/view/agriculture/irrigation.py
sparcs/application/view/agriculture/soil.py
sparcs/application/view/storage/__init__.py
sparcs/application/view/storage/water.py
sparcs/components/__init__.py
sparcs/components/agriculture/__init__.py
sparcs/components/agriculture/area.py
sparcs/components/agriculture/field.py
sparcs/components/agriculture/irrigation.py
sparcs/components/agriculture/soil/__init__.py
sparcs/components/agriculture/soil/models.py
sparcs/components/agriculture/soil/moisture.py
sparcs/components/agriculture/solar/__init__.py
sparcs/components/agriculture/solar/array.py
sparcs/components/agriculture/solar/system.py
sparcs/components/solar/__init__.py
sparcs/components/solar/array.py
sparcs/components/solar/inverter.py
sparcs/components/solar/model.py
sparcs/components/solar/system.py
sparcs/components/solar/db/__init__.py
sparcs/components/solar/db/base.py
sparcs/components/solar/db/cec.py
sparcs/components/storage/__init__.py
sparcs/components/storage/electrical.py
sparcs/components/storage/thermal.py
sparcs/components/storage/water.py
sparcs/components/weather/__init__.py
sparcs/components/weather/input.py
sparcs/components/weather/static/__init__.py
sparcs/components/weather/static/epw.py
sparcs/components/weather/static/file.py
sparcs/components/weather/static/tmy.py
sparcs-0.5.0.dist-info/licenses/LICENSE
sparcs-0.5.0.dist-info/METADATA
sparcs-0.5.0.dist-info/WHEEL
sparcs-0.5.0.dist-info/entry_points.txt
sparcs-0.5.0.dist-info/top_level.txt
sparcs-0.5.0.dist-info/RECORD
