Metadata-Version: 2.4
Name: sparcs
Version: 0.5.0
Summary: This project provides a set of functions and applications for Solar Prediction, Analytics and Resource Control Systems by ISC Konstanz e.V.
Author: ISC Konstanz e.V.
Maintainer-email: Adrian Minde <adrian.minde@isc-konstanz.de>
License-Expression: GPL-3.0-or-later
Project-URL: author, https://isc-konstanz.de
Project-URL: source, https://github.com/isc-konstanz/sparcs/
Project-URL: issues, https://github.com/isc-konstanz/sparcs/issues
Classifier: Programming Language :: Python :: 3
Classifier: Programming Language :: Python :: 3 :: Only
Classifier: Programming Language :: Python :: 3.9
Classifier: Programming Language :: Python :: 3.10
Classifier: Programming Language :: Python :: 3.11
Classifier: Programming Language :: Python :: 3.12
Classifier: Programming Language :: Python :: 3.13
Classifier: Operating System :: OS Independent
Requires-Python: >=3.9
License-File: LICENSE
Requires-Dist: lories>=0.15
Requires-Dist: pvlib>=0.10.1
Requires-Dist: NREL-PySAM>=4.0
Provides-Extra: dev
Requires-Dist: pre-commit; extra == "dev"
Requires-Dist: ruff; extra == "dev"
Dynamic: license-file
